TP2/Verilog/media_amostras.v
module media_amostras (
    input            clk,
    input            rst,
    input      [7:0] amostra_nova,
    output reg [7:0] media
);

    reg [7:0] amostra_atual;
    reg [7:0] amostra_anterior;

    always @(posedge clk) begin
        if (rst) begin
            amostra_atual    <= 8'b0;
            amostra_anterior <= 8'b0;
            media            <= 8'b0;
        end else begin
            amostra_anterior <= amostra_atual;
            amostra_atual    <= amostra_nova;
            media            <= (amostra_atual + amostra_anterior) >> 1;
        end
    end

endmodule

TP2/Verilog/media_amostras_tb.v
`timescale 1ns/1ps

module media_amostras_tb;

    reg        clk;
    reg        rst;
    reg  [7:0] amostra_nova;
    wire [7:0] media;

    media_amostras uut (
        .clk         (clk),
        .rst         (rst),
        .amostra_nova(amostra_nova),
        .media       (media)
    );

    always #5 clk = ~clk;

    initial begin
        $dumpfile("media_amostras.vcd");
        $dumpvars(0, media_amostras_tb);

        clk          = 1'b0;
        rst          = 1'b1;
        amostra_nova = 8'b0;

        #20;
        rst = 1'b0;

        $display("Iniciando simulacao do modulo de media de duas amostras");
        $display("----------------------------------------------------------");

        amostra_nova = 8'd20;
        @(posedge clk); #1;
        $display("Amostra nova = %0d | Media = %0d", amostra_nova, media);

        amostra_nova = 8'd40;
        @(posedge clk); #1;
        $display("Amostra nova = %0d | Media = %0d", amostra_nova, media);

        amostra_nova = 8'd30;
        @(posedge clk); #1;
        $display("Amostra nova = %0d | Media = %0d", amostra_nova, media);

        amostra_nova = 8'd60;
        @(posedge clk); #1;
        $display("Amostra nova = %0d | Media = %0d", amostra_nova, media);

        amostra_nova = 8'd72;
        @(posedge clk); #1;
        $display("Amostra nova = %0d | Media = %0d", amostra_nova, media);

        amostra_nova = 8'd28;
        @(posedge clk); #1;
        $display("Amostra nova = %0d | Media = %0d", amostra_nova, media);

        $display("----------------------------------------------------------");
        $display("Simulacao concluida.");
        $finish;
    end

endmodule

TP2/Verilog/media_amostras.vcd
$date
	Fri Jun 19 10:38:53 2026
$end
$version
	Icarus Verilog
$end
$timescale
	1ps
$end
$scope module media_amostras_tb $end
$var wire 8 ! media [7:0] $end
$var reg 8 " amostra_nova [7:0] $end
$var reg 1 # clk $end
$var reg 1 $ rst $end
$scope module uut $end
$var wire 8 % amostra_nova [7:0] $end
$var wire 1 # clk $end
$var wire 1 $ rst $end
$var reg 8 & amostra_anterior [7:0] $end
$var reg 8 ' amostra_atual [7:0] $end
$var reg 8 ( media [7:0] $end
$upscope $end
$upscope $end
$enddefinitions $end
$comment Show the parameter values. $end
$dumpall
$end
#0
$dumpvars
bx (
bx '
bx &
b0 %
1$
0#
b0 "
bx !
$end
#5000
b0 !
b0 (
b0 &
b0 '
1#
#10000
0#
#15000
1#
#20000
0#
b10100 "
b10100 %
0$
#25000
b10100 '
1#
#26000
b101000 "
b101000 %
#30000
0#
#35000
b1010 !
b1010 (
b101000 '
b10100 &
1#
#36000
b11110 "
b11110 %
#40000
0#
#45000
b11110 !
b11110 (
b11110 '
b101000 &
1#
#46000
b111100 "
b111100 %
#50000
0#
#55000
b100011 !
b100011 (
b111100 '
b11110 &
1#
#56000
b1001000 "
b1001000 %
#60000
0#
#65000
b101101 !
b101101 (
b1001000 '
b111100 &
1#
#66000
b11100 "
b11100 %
#70000
0#
#75000
b1000010 !
b1000010 (
b11100 '
b1001000 &
1#
