TP3/Verilog/fsm_controle_leitura.v
module fsm_controle_leitura (
    input  wire clk,
    input  wire rst,
    input  wire start,
    input  wire dado_pronto,
    output reg  canal_sel,
    output reg  amostrar,
    output reg  transmitir
);

    localparam OCIOSO    = 2'b00;
    localparam AMOSTRA   = 2'b01;
    localparam TRANSMITE = 2'b10;

    localparam SOLO         = 1'b0;
    localparam LUMINOSIDADE = 1'b1;

    reg [1:0] estado;

    always @(posedge clk or posedge rst) begin
        if (rst) begin
            estado     <= OCIOSO;
            canal_sel  <= SOLO;
            amostrar   <= 1'b0;
            transmitir <= 1'b0;
        end else begin
            case (estado)
                OCIOSO: begin
                    amostrar   <= 1'b0;
                    transmitir <= 1'b0;
                    if (start) begin
                        estado <= AMOSTRA;
                    end else begin
                        estado <= OCIOSO;
                    end
                end

                AMOSTRA: begin
                    amostrar   <= 1'b1;
                    transmitir <= 1'b0;
                    if (dado_pronto) begin
                        estado <= TRANSMITE;
                    end else begin
                        estado <= AMOSTRA;
                    end
                end

                TRANSMITE: begin
                    amostrar   <= 1'b0;
                    transmitir <= 1'b1;
                    if (canal_sel == SOLO) begin
                        canal_sel <= LUMINOSIDADE;
                        estado    <= AMOSTRA;
                    end else begin
                        canal_sel <= SOLO;
                        estado    <= OCIOSO;
                    end
                end

                default: begin
                    estado <= OCIOSO;
                end
            endcase
        end
    end

endmodule

TP3/Verilog/fsm_controle_leitura_tb.v
module fsm_controle_leitura_tb;

    reg clk;
    reg rst;
    reg start;
    reg dado_pronto;
    wire canal_sel;
    wire amostrar;
    wire transmitir;

    fsm_controle_leitura uut (
        .clk(clk),
        .rst(rst),
        .start(start),
        .dado_pronto(dado_pronto),
        .canal_sel(canal_sel),
        .amostrar(amostrar),
        .transmitir(transmitir)
    );

    always #5 clk = ~clk;

    initial begin
        $dumpfile("fsm_controle_leitura.vcd");
        $dumpvars(0, fsm_controle_leitura_tb);

        clk = 0;
        rst = 1;
        start = 0;
        dado_pronto = 0;
        #10;
        rst = 0;

        #10 start = 1;
        #10 start = 0;

        #10 dado_pronto = 1;
        #10 dado_pronto = 0;

        #10 dado_pronto = 1;
        #10 dado_pronto = 0;

        #10 start = 1;
        #10 start = 0;

        #10 dado_pronto = 1;
        #10 dado_pronto = 0;

        #10 dado_pronto = 1;
        #10 dado_pronto = 0;

        #20 $finish;
    end

endmodule

TP3/Verilog/fsm_controle_leitura.vcd
$date
	Fri Aug 07 22:24:56 2026
$end
$version
	Icarus Verilog
$end
$timescale
	1s
$end
$scope module fsm_controle_leitura_tb $end
$var wire 1 ! transmitir $end
$var wire 1 " canal_sel $end
$var wire 1 # amostrar $end
$var reg 1 $ clk $end
$var reg 1 % dado_pronto $end
$var reg 1 & rst $end
$var reg 1 ' start $end
$scope module uut $end
$var wire 1 $ clk $end
$var wire 1 % dado_pronto $end
$var wire 1 & rst $end
$var wire 1 ' start $end
$var parameter 2 ( AMOSTRA $end
$var parameter 1 ) LUMINOSIDADE $end
$var parameter 2 * OCIOSO $end
$var parameter 1 + SOLO $end
$var parameter 2 , TRANSMITE $end
$var reg 1 # amostrar $end
$var reg 1 " canal_sel $end
$var reg 2 - estado [1:0] $end
$var reg 1 ! transmitir $end
$upscope $end
$upscope $end
$enddefinitions $end
$comment Show the parameter values. $end
$dumpall
b10 ,
0+
b0 *
1)
b1 (
$end
#0
$dumpvars
b0 -
0'
1&
0%
0$
0#
0"
0!
$end
#5
1$
#10
0$
0&
#15
1$
#20
0$
1'
#25
b1 -
1$
#30
0$
0'
#35
1#
1$
#40
0$
1%
#45
b10 -
1$
#50
0$
0%
#55
b1 -
1"
1!
0#
1$
#60
0$
1%
#65
b10 -
0!
1#
1$
#70
0$
0%
#75
b0 -
0"
1!
0#
1$
#80
0$
1'
#85
b1 -
0!
1$
#90
0$
0'
#95
1#
1$
#100
0$
1%
#105
b10 -
1$
#110
0$
0%
#115
b1 -
1"
1!
0#
1$
#120
0$
1%
#125
b10 -
0!
1#
1$
#130
0$
0%
#135
b0 -
0"
1!
0#
1$
#140
0$
#145
0!
1$
